sb_models/__init__.py
sb_models/animatediff/animatediff.py
sb_models/animatediff/animatediff_sdxl.py
sb_models/animatediff/animatediff_video.py
sb_models/animatediff/animatediff_video_toon.py
sb_models/api.py
sb_models/assets/assets.py
sb_models/bakllava/bakllava.py
sb_models/bark/bark.py
sb_models/clip/clip.py
sb_models/compose/compose.py
sb_models/config.py
sb_models/conftest.py
sb_models/control_aux.py
sb_models/coqui/serve.py
sb_models/coqui/xtts.py
sb_models/datadog.py
sb_models/db.py
sb_models/debug.py
sb_models/disk_utils.py
sb_models/dreambooth/dreambooth.py
sb_models/dreambooth/instance_example_urls.txt
sb_models/esrgan/esrgan.py
sb_models/falcon/falcon_30_bnb.py
sb_models/fallback/anyscale.py
sb_models/firellava/firellava.py
sb_models/firellava/serve.py
sb_models/flag_embedding/bge_base_1_5.py
sb_models/flag_embedding/bge_large_1_5.py
sb_models/gligen/gligen.py
sb_models/gligen/gligen_inpaint.py
sb_models/graph/README-graph.md
sb_models/graph/__init__.py
sb_models/graph/adapters.py
sb_models/graph/edge.py
sb_models/graph/find_futures_server.py
sb_models/graph/graph_result.py
sb_models/graph/modal_nodes.py
sb_models/graph/node.py
sb_models/graph/public_nodes.py
sb_models/graph/server_future.py
sb_models/graph/server_graph.py
sb_models/graph/util.py
sb_models/grounding_dino/grounding_dino_base.py
sb_models/grounding_dino/grounding_dino_tiny.py
sb_models/hash.py
sb_models/image_utils.py
sb_models/jina_embedding/jina_base_v2.py
sb_models/lama/lama.py
sb_models/llama/llama_tgi.py
sb_models/llama/llama_vllm.py
sb_models/llama/llm-frontend/index.html
sb_models/logger.py
sb_models/mistral/mistral_7b_instruct.py
sb_models/mistral/mistral_tgi.py
sb_models/mistral/mixtral_8x7b_instruct.py
sb_models/network.py
sb_models/python_node/python_node.py
sb_models/rembg/isnet.py
sb_models/sam/sam.py
sb_models/sample_math_app/.gitignore
sb_models/sample_math_app/autoscaling/blocked.py
sb_models/sample_math_app/autoscaling/blocked_new.py
substratecore-20240311.0.dist-info/METADATA
substratecore-20240311.0.dist-info/WHEEL
substratecore-20240311.0.dist-info/RECORD
