Metadata-Version: 2.1
Name: substratecore
Version: 20240311.0
Summary: Autogenerated models and serialization for the Substrate API and SDKs
Author: vprtwn
Author-email: ben@substrate.run
Requires-Python: >=3.10,<4
Classifier: Programming Language :: Python :: 3
Classifier: Programming Language :: Python :: 3.10
Classifier: Programming Language :: Python :: 3.11
Classifier: Programming Language :: Python :: 3.12
Requires-Dist: fastapi (>=0.108.0,<0.109.0)
Requires-Dist: modal (==0.60.7)
Requires-Dist: networkx (==3.2.1)
Requires-Dist: numpy (==1.26.2)
Requires-Dist: pydantic (<2.0.0)
Requires-Dist: ray[serve] (==2.9.3)
